netbox_client/__init__.py
netbox_client/api_client.py
netbox_client/configuration.py
netbox_client/rest.py
netbox_client/api/__init__.py
netbox_client/api/circuits_api.py
netbox_client/api/dcim_api.py
netbox_client/api/extras_api.py
netbox_client/api/ipam_api.py
netbox_client/api/secrets_api.py
netbox_client/api/tenancy_api.py
netbox_client/api/virtualization_api.py
netbox_client/models/__init__.py
netbox_client/models/action.py
netbox_client/models/aggregate.py
netbox_client/models/available_ip.py
netbox_client/models/available_prefix.py
netbox_client/models/cable.py
netbox_client/models/circuit.py
netbox_client/models/circuit_circuit_termination.py
netbox_client/models/circuit_termination.py
netbox_client/models/circuit_type.py
netbox_client/models/cluster.py
netbox_client/models/cluster_group.py
netbox_client/models/cluster_type.py
netbox_client/models/config_context.py
netbox_client/models/connection_status.py
netbox_client/models/console_port.py
netbox_client/models/console_port_template.py
netbox_client/models/console_server_port.py
netbox_client/models/console_server_port_template.py
netbox_client/models/device.py
netbox_client/models/device_bay.py
netbox_client/models/device_bay_template.py
netbox_client/models/device_interface.py
netbox_client/models/device_napalm.py
netbox_client/models/device_role.py
netbox_client/models/device_type.py
netbox_client/models/device_with_config_context.py
netbox_client/models/export_template.py
netbox_client/models/face.py
netbox_client/models/family.py
netbox_client/models/feed_leg.py
netbox_client/models/front_port.py
netbox_client/models/front_port_rear_port.py
netbox_client/models/front_port_template.py
netbox_client/models/graph.py
netbox_client/models/image_attachment.py
netbox_client/models/inline_response200.py
netbox_client/models/inline_response2001.py
netbox_client/models/inline_response20010.py
netbox_client/models/inline_response20011.py
netbox_client/models/inline_response20012.py
netbox_client-1.0.3.dist-info/LICENSE
netbox_client-1.0.3.dist-info/METADATA
netbox_client-1.0.3.dist-info/WHEEL
netbox_client-1.0.3.dist-info/top_level.txt
netbox_client-1.0.3.dist-info/RECORD
