Metadata-Version: 2.1
Name: netbox-client
Version: 1.0.3
Summary: NetBox API Client
Home-page: https://github.com/nrfta/python-netbox-client
Maintainer: strobus
License: UNKNOWN
Keywords: Swagger,NetBox
Platform: UNKNOWN
Classifier: Programming Language :: Python
Classifier: Development Status :: 4 - Beta
Classifier: License :: OSI Approved :: MIT License
Classifier: Operating System :: OS Independent
Requires-Dist: certifi (>=2017.4.17)
Requires-Dist: python-dateutil (>=2.1)
Requires-Dist: six (>=1.10)
Requires-Dist: urllib3 (>=1.23)
